MANIFEST.in
README.rst
isit.py
setup.py
isit.egg-info/PKG-INFO
isit.egg-info/SOURCES.txt
isit.egg-info/dependency_links.txt
isit.egg-info/top_level.txt