Metadata-Version: 1.1
Name: isit
Version: 0.3.6
Summary: Environment runtime detection (Python,Linux,Distribution,etc...)
Home-page: https://github.com/toxinu/isit
Author: toxinu
Author-email: toxinu@gmail.com
License: UNKNOWN
Keywords: python linux env variable windows arch distribution
Platform: UNKNOWN
Classifier: Development Status :: 4 - Beta
Classifier: License :: OSI Approved :: GNU Affero General Public License v3 or later (AGPLv3+)
Classifier: Programming Language :: Python
Classifier: Programming Language :: Python :: 2
Classifier: Programming Language :: Python :: 2.4
Classifier: Programming Language :: Python :: 2.5
Classifier: Programming Language :: Python :: 2.6
Classifier: Programming Language :: Python :: 2.7
Classifier: Programming Language :: Python :: 3
Classifier: Programming Language :: Python :: 3.0
Classifier: Programming Language :: Python :: 3.1
Classifier: Programming Language :: Python :: 3.2
Classifier: Programming Language :: Python :: 3.3
